iniknumber/__init__.py
iniknumber/checker.py
iniknumber/data/location_data.csv
iniknumber-0.1.0.dist-info/LICENSE
iniknumber-0.1.0.dist-info/METADATA
iniknumber-0.1.0.dist-info/WHEEL
iniknumber-0.1.0.dist-info/top_level.txt
iniknumber-0.1.0.dist-info/RECORD
