Metadata-Version: 2.1
Name: iniknumber
Version: 0.1.0
Summary: A Python package for parsing and validating NIK numbers.
Home-page: https://github.com/yourusername/iniknumber
Author: irwannafly13
Author-email: anggadventurez@gmail.com
Classifier: Programming Language :: Python :: 3
Classifier: License :: OSI Approved :: MIT License
Classifier: Operating System :: OS Independent
Requires-Python: >=3.6
License-File: LICENSE
Requires-Dist: pandas
